graph_poitool/__init__.py
graph_poitool/cli.py
graph_poitool/utils.py
graph_poitool/clients/__init__.py
graph_poitool/clients/ebo/__init__.py
graph_poitool/clients/ebo/base_client.py
graph_poitool/clients/ebo/base_model.py
graph_poitool/clients/ebo/client.py
graph_poitool/clients/ebo/current_epoch.py
graph_poitool/clients/ebo/enums.py
graph_poitool/clients/ebo/input_types.py
graph_poitool/clients/ebo/mixins.py
graph_poitool/clients/gql/__init__.py
graph_poitool/clients/gql/base_client.py
graph_poitool/clients/gql/base_model.py
graph_poitool/clients/gql/exceptions.py
graph_poitool/clients/indexer_status/__init__.py
graph_poitool/clients/indexer_status/base_client.py
graph_poitool/clients/indexer_status/base_model.py
graph_poitool/clients/indexer_status/block_data.py
graph_poitool/clients/indexer_status/block_hash.py
graph_poitool/clients/indexer_status/cached_ethereum_calls.py
graph_poitool/clients/indexer_status/client.py
graph_poitool/clients/indexer_status/entity_changes.py
graph_poitool/clients/indexer_status/enums.py
graph_poitool/clients/indexer_status/input_types.py
graph_poitool/clients/indexer_status/mixins.py
graph_poitool/clients/indexer_status/public_poi.py
graph_poitool/clients/indexer_status/subgraph_status.py
graph_poitool/clients/indexer_status/synced_subgraphs.py
graph_poitool/clients/network/__init__.py
graph_poitool/clients/network/base_client.py
graph_poitool/clients/network/base_model.py
graph_poitool/clients/network/client.py
graph_poitool/clients/network/enums.py
graph_poitool/clients/network/indexer.py
graph_poitool/clients/network/indexers.py
graph_poitool/clients/network/input_types.py
graph_poitool/clients/network/manifest.py
graph_poitool/clients/network/mixins.py
graph_poitool/clients/network/subgraph_allocations.py
graph_poitool/clients/network/subgraph_deployment_manifest.py
graph_poitool/services/__init__.py
graph_poitool/services/bisect/__init__.py
graph_poitool/services/bisect/exceptions.py
graph_poitool/services/bisect/service.py
graph_poitool-0.1.3.dist-info/METADATA
graph_poitool-0.1.3.dist-info/WHEEL
graph_poitool-0.1.3.dist-info/entry_points.txt
graph_poitool-0.1.3.dist-info/licenses/LICENSE.md
graph_poitool-0.1.3.dist-info/RECORD
