Metadata-Version: 2.4
Name: graph-poitool
Version: 0.1.3
Author: P2P.ORG
License-Expression: MIT
License-File: LICENSE.md
Requires-Python: <4,>=3.10
Requires-Dist: click<9.0.0,>=8.2.1
Requires-Dist: httpx<0.29.0,>=0.28.1
Requires-Dist: pydantic<3.0.0,>=2.11.7
Requires-Dist: rich<15.0.0,>=14.1.0
